aiflow/AiService.py
aiflow/__init__.py
aiflow/constants.py
aiflow/utils.py
aiworkflow-0.0.4.dist-info/LICENSE
aiworkflow-0.0.4.dist-info/METADATA
aiworkflow-0.0.4.dist-info/WHEEL
aiworkflow-0.0.4.dist-info/top_level.txt
aiworkflow-0.0.4.dist-info/RECORD
