Metadata-Version: 2.1
Name: aiworkflow
Version: 0.0.4
Summary: Python Client to access Navigator
Home-page: https://navigator.pyxeda.ai
Author: Pyxeda AI
Author-email: support@pyxeda.ai
License: UNKNOWN
Platform: UNKNOWN
Classifier: Programming Language :: Python :: 3
Classifier: License :: OSI Approved :: MIT License
Classifier: Operating System :: OS Independent
Requires-Python: >=3.6
